python_ew
