Metadata-Version: 2.1
Name: python-ew
Version: 2.1.5
Summary: Allow reading from and writing to Earthworm shared memory ring buffers.
Home-page: https://github.com/caltechads/python-ew
Author: Caltech IMSS ADS
Author-email: imss-ads-staff@caltech.edu
License: UNKNOWN
Project-URL: Home Page, https://github.com/caltechads/python-ew
Project-URL: Bug Tracker, https://github.com/caltechads/python-ew/issues
Project-URL: Documentation, https://github.com/caltechads/python-ew
Platform: UNKNOWN
Classifier: Development Status :: 5 - Production/Stable
Classifier: Intended Audience :: Developers
Classifier: Intended Audience :: Science/Research
Classifier: License :: OSI Approved :: GNU General Public License v3 (GPLv3)
Classifier: Operating System :: POSIX
Classifier: Programming Language :: Python :: 3.6
Classifier: Programming Language :: Python :: 3.7
Classifier: Topic :: Scientific/Engineering
Classifier: Topic :: Software Development :: Libraries :: Python Modules
Classifier: Topic :: Software Development :: Libraries
Requires-Python: >=3.6
